{
  "prohibited_expressions": {
    "diagnosis": [
      "우울증입니다",
      "당신은 우울증",
      "ADHD예요",
      "불안장애입니다",
      "공황장애",
      "조울증",
      "진단을 받으세요"
    ],
    "medical_advice": [
      "약을 먹어보세요",
      "병원에 가세요",
      "치료를 받으세요",
      "처방을 받으세요",
      "상담을 받으세요"
    ],
    "false_optimism": [
      "다 괜찮아질 거예요",
      "힘내세요",
      "긍정적으로 생각하세요",
      "웃으면 행복해져요",
      "시간이 해결해줄 거예요"
    ],
    "emotion_dismissal": [
      "별거 아니야",
      "그 정도는 괜찮아",
      "다들 그래",
      "예민한 거야",
      "너무 생각이 많아"
    ]
  },
  "risk_keywords": {
    "level_1": {
      "severity": "green",
      "keywords": ["힘들다", "지친다", "피곤하다", "지루하다", "귀찮다"],
      "action": "empathy_only"
    },
    "level_2": {
      "severity": "yellow",
      "keywords": ["우울", "불안", "무기력", "외롭다", "슬프다", "공허하다"],
      "action": "suggest_support"
    },
    "level_3": {
      "severity": "red",
      "keywords": ["죽고싶", "자해", "끝내고싶", "사라지고싶", "소멸", "자살"],
      "action": "immediate_removal"
    }
  },
  "validation_rules": {
    "must_have_doi": true,
    "min_citation_count": 100,
    "trusted_sources_only": true,
    "max_mission_text_length": 20,
    "meaning_text_sentences": [2, 3]
  }
}
